superstore/__init__.py
superstore/crossfilter.py
superstore/superstore.py
superstore/utils.py
superstore/csp/__init__.py
superstore/csp/crossfilter.py
superstore/tests/__init__.py
superstore/tests/test_crossfilter.py
superstore/tests/test_superstore.py
superstore/tests/test_vendored.py
superstore/tests/csp/__init__.py
superstore/tests/csp/test_crossfilter.py
superstore/vendored/__init__.py
superstore/vendored/timeseries.py
superstore-0.2.6.dist-info/AUTHORS
superstore-0.2.6.dist-info/LICENSE
superstore-0.2.6.dist-info/METADATA
superstore-0.2.6.dist-info/WHEEL
superstore-0.2.6.dist-info/top_level.txt
superstore-0.2.6.dist-info/RECORD
