Metadata-Version: 2.1
Name: superstore
Version: 0.2.6
Summary: Data generation
Author-email: Tim Paine <t.paine154@gmail.com>
License: Apache License
Project-URL: repository, https://github.com/timkpaine/superstore
Project-URL: homepage, https://github.com/timkpaine/superstore
Keywords: Jupyter,JupyterLab,Notebook,Notebooks,Report,Reports,Reporting
Classifier: Development Status :: 4 - Beta
Classifier: Programming Language :: Python
Classifier: Programming Language :: Python :: 3
Classifier: Programming Language :: Python :: 3.9
Classifier: Programming Language :: Python :: 3.10
Classifier: Programming Language :: Python :: 3.11
Classifier: Programming Language :: Python :: 3.12
Classifier: License :: OSI Approved :: Apache Software License
Requires-Python: >=3.7
License-File: LICENSE
License-File: AUTHORS
Requires-Dist: coolname
Requires-Dist: Faker>=1.0.1
Requires-Dist: pandas>=0.23.4
Provides-Extra: develop
Requires-Dist: bump-my-version; extra == "develop"
Requires-Dist: check-manifest; extra == "develop"
Requires-Dist: isort<6,>=5; extra == "develop"
Requires-Dist: ruff<0.5,>=0.3; extra == "develop"
Requires-Dist: csp; extra == "develop"
Requires-Dist: pytest; extra == "develop"
Requires-Dist: pytest-cov; extra == "develop"
Provides-Extra: test
Requires-Dist: pytest; extra == "test"
Requires-Dist: pytest-cov; extra == "test"
